test/__init__.py
test/run_coveralls.py
test/test_corrections.py
use_logging/__init__.py
use_logging/__main__.py
use_logging/fixes/__init__.py
use_logging/fixes/base.py
use_logging/fixes/fix_print_new.py
use_logging/fixes/fix_print_old.py
use_logging-0.0.1.data/scripts/use_logging
use_logging-0.0.1.dist-info/DESCRIPTION.rst
use_logging-0.0.1.dist-info/METADATA
use_logging-0.0.1.dist-info/RECORD
use_logging-0.0.1.dist-info/WHEEL
use_logging-0.0.1.dist-info/metadata.json
use_logging-0.0.1.dist-info/top_level.txt
