Metadata-Version: 2.0
Name: use-logging
Version: 0.0.1
Summary: Tool for changing python print statements into logging module invocations. Automatically adds the appropriate imports.
Home-page: https://github.com/GambitResearch/use_logging
Author: Daniel Royde
Author-email: danielroyde@gmail.com
License: MIT
Keywords: Python,Logging
Platform: UNKNOWN
